Workbook

Sheet 补货清单
A1: 📦 补货清单 — Replenishment Worksheet
A2: 本表汇总全部SKU库存状态。缺货/不足项排前。在「本次补货数量」列填入数量，金额自动计算。黄色底=需补货。绿色底=库存充足暂无需补。
A3: 序号 | B3: 商品编号 | C3: 品类 | D3: 品牌 | E3: 款式名称 | F3: 尺码 | G3: 颜色 | H3: 存放位置 | I3: 当前库存 | J3: 安全库存 | K3: 建议补货量 | L3: 库存状态 | M3: 供应商 | N3: 成本单价(SGD) | O3: 本次补货数量 | P3: 补货金额(SGD) | Q3: 备注
A4: 1 | B4: BR-001 | C4: 内衣 | D4: Triumph | E4: 无钢圈舒适文胸 | F4: 36B | G4: 肤色 | I4: =库存总览!J5 | J4: =库存总览!K5 | K4: =库存总览!L5 | L4: 缺货 | M4: Triumph SG | N4: 10.5 | P4: =IF(O4="","",O4*N4)
A5: 2 | B5: BR-001 | C5: 内衣 | D5: Triumph | E5: 无钢圈舒适文胸 | F5: 34C | G5: 黑色 | I5: =库存总览!J6 | J5: =库存总览!K6 | K5: =库存总览!L6 | L5: 缺货 | M5: Triumph SG | N5: 10.5 | P5: =IF(O5="","",O5*N5)
A6: 3 | B6: BR-004 | C6: 内衣 | D6: Wacoal | E6: 聚拢调整型文胸 | F6: 36C | G6: 肤色 | I6: =库存总览!J8 | J6: =库存总览!K8 | K6: =库存总览!L8 | L6: 缺货 | M6: Wacoal 代理 | N6: 14 | P6: =IF(O6="","",O6*N6)
A7: 4 | B7: UN-001 | C7: 内裤 | D7: Byford | E7: 纯棉平角内裤(男) | F7: M | G7: 灰色 | H7: B架-1层 | I7: =库存总览!J9 | J7: =库存总览!K9 | K7: =库存总览!L9 | L7: 缺货 | M7: Byford 批发 | N7: 4.5 | P7: =IF(O7="","",O7*N7)
A8: 5 | B8: UN-001 | C8: 内裤 | D8: Byford | E8: 纯棉平角内裤(男) | F8: L | G8: 灰色 | I8: =库存总览!J10 | J8: =库存总览!K10 | K8: =库存总览!L10 | L8: 缺货 | M8: Byford 批发 | N8: 4.5 | P8: =IF(O8="","",O8*N8)
A9: 6 | B9: UN-001 | C9: 内裤 | D9: Byford | E9: 纯棉平角内裤(男) | F9: XL | G9: 黑色 | I9: =库存总览!J11 | J9: =库存总览!K11 | K9: =库存总览!L11 | L9: 缺货 | M9: Byford 批发 | N9: 4.5 | P9: =IF(O9="","",O9*N9)
A10: 7 | B10: UN-004 | C10: 内裤 | D10: Renoma | E10: 冰丝三角内裤(男) | F10: L | G10: 黑色 | I10: =库存总览!J13 | J10: =库存总览!K13 | K10: =库存总览!L13 | L10: 缺货 | M10: Renoma 总代 | N10: 3.2 | P10: =IF(O10="","",O10*N10)
A11: 8 | B11: UN-006 | C11: 内裤 | D11: Triumph | E11: 蕾丝三角内裤(女) | F11: L | G11: 肤色 | I11: =库存总览!J15 | J11: =库存总览!K15 | K11: =库存总览!L15 | L11: 缺货 | M11: Triumph SG | N11: 3.8 | P11: =IF(O11="","",O11*N11)
A12: 9 | B12: SK-001 | C12: 袜子 | D12: Goldlion | E12: 商务棉袜 3双装 | F12: 均码 | G12: 深灰 | I12: =库存总览!J17 | J12: =库存总览!K17 | K12: =库存总览!L17 | L12: 缺货 | M12: Goldlion 批发 | N12: 2.5 | P12: =IF(O12="","",O12*N12)
A13: 10 | B13: ST-001 | C13: 裤袜 | D13: Gunze | E13: 发热保暖连裤袜 | F13: L-LL | G13: 深灰 | I13: =库存总览!J22 | J13: =库存总览!K22 | K13: =库存总览!L22 | L13: 缺货 | M13: Gunze 日本 | N13: 8 | P13: =IF(O13="","",O13*N13)
A14: 11 | B14: UN-006 | C14: 内裤 | D14: Triumph | E14: 蕾丝三角内裤(女) | F14: M | G14: 粉色 | H14: B架-3层 | I14: =库存总览!J14 | J14: =库存总览!K14 | K14: =库存总览!L14 | L14: 不足 | M14: Triumph SG | N14: 3.8 | P14: =IF(O14="","",O14*N14)
A15: 12 | B15: SK-001 | C15: 袜子 | D15: Goldlion | E15: 商务棉袜 3双装 | F15: 均码 | G15: 黑色 | H15: C架-1层 | I15: =库存总览!J16 | J15: =库存总览!K16 | K15: =库存总览!L16 | L15: 不足 | M15: Goldlion 批发 | N15: 2.5 | P15: =IF(O15="","",O15*N15)
A16: 13 | B16: SK-003 | C16: 袜子 | D16: Puma | E16: 运动短袜(男) | F16: 均码 | G16: 白色 | H16: C架-2层 | I16: =库存总览!J18 | J16: =库存总览!K18 | K16: =库存总览!L18 | L16: 不足 | M16: Puma 经销商 | N16: 3 | P16: =IF(O16="","",O16*N16)
A17: 14 | B17: SK-004 | C17: 袜子 | D17: Puma | E17: 运动短袜(女) | F17: 均码 | G17: 白色 | H17: C架-2层 | I17: =库存总览!J19 | J17: =库存总览!K19 | K17: =库存总览!L19 | L17: 不足 | M17: Puma 经销商 | N17: 3 | P17: =IF(O17="","",O17*N17)
A18: 15 | B18: SK-005 | C18: 袜子 | D18: Happy Socks | E18: 彩色棉袜(女) | F18: 均码 | G18: 花色 | H18: C架-3层 | I18: =库存总览!J20 | J18: =库存总览!K20 | K18: =库存总览!L20 | L18: 不足 | M18: Happy Socks SG | N18: 3.5 | P18: =IF(O18="","",O18*N18)
A19: 16 | B19: BR-001 | C19: 内衣 | D19: Triumph | E19: 无钢圈舒适文胸 | F19: 34B | G19: 黑色 | H19: A架-1层 | I19: =库存总览!J4 | J19: =库存总览!K4 | K19: =库存总览!L4 | L19: 充足 | M19: Triumph SG | N19: 10.5 | P19: =IF(O19="","",O19*N19)
A20: 17 | B20: BR-004 | C20: 内衣 | D20: Wacoal | E20: 聚拢调整型文胸 | F20: 34B | G20: 黑色 | H20: A架-2层 | I20: =库存总览!J7 | J20: =库存总览!K7 | K20: =库存总览!L7 | L20: 充足 | M20: Wacoal 代理 | N20: 14 | P20: =IF(O20="","",O20*N20)
A21: 18 | B21: UN-004 | C21: 内裤 | D21: Renoma | E21: 冰丝三角内裤(男) | F21: M | G21: 蓝色 | H21: B架-2层 | I21: =库存总览!J12 | J21: =库存总览!K12 | K21: =库存总览!L12 | L21: 充足 | M21: Renoma 总代 | N21: 3.2 | P21: =IF(O21="","",O21*N21)
A22: 19 | B22: ST-001 | C22: 裤袜 | D22: Gunze | E22: 发热保暖连裤袜 | F22: M-L | G22: 黑色 | H22: D架-1层 | I22: =库存总览!J21 | J22: =库存总览!K21 | K22: =库存总览!L21 | L22: 充足 | M22: Gunze 日本 | N22: 8 | P22: =IF(O22="","",O22*N22)
A23: 20 | B23: ST-003 | C23: 裤袜 | D23: Atsugi | E23: 压力美腿连裤袜 | F23: M-L | G23: 肤色 | H23: D架-2层 | I23: =库存总览!J23 | J23: =库存总览!K23 | K23: =库存总览!L23 | L23: 充足 | M23: Atsugi 代理 | N23: 10 | P23: =IF(O23="","",O23*N23)
A26: 📊 补货汇总
O27: 补货总数量 | P27: 补货总金额(SGD)
O28: =SUM(O4:O23) | P28: =SUM(P4:P23)
A30: 状态统计: | E30: 🔴 缺货: 10 项 | H30: 🟡 不足: 5 项 | K30: 🟢 充足: 5 项

Sheet 商品目录
A1: 商品目录 — Product Catalog
A2: 维护所有商品信息。款式+颜色+尺码为最小管理单位。新增商品在最下方添加。
A3: 商品编号 | B3: 品类 | C3: 品牌 | D3: 款式名称 | E3: 尺码 | F3: 颜色 | G3: 存放位置 | H3: 零售价(SGD) | I3: 批发价(SGD) | J3: 成本价(SGD) | K3: 安全库存 | L3: 当前库存 | M3: 备注
A4: BR-001 | B4: 内衣 | C4: Triumph | D4: 无钢圈舒适文胸 | E4: 34B | F4: 黑色 | G4: A架-1层 | H4: 19.9 | I4: 16.9 | J4: 10.5 | K4: 5 | L4: 8
E5: 36B | F5: 肤色 | H5: 19.9 | I5: 16.9 | J5: 10.5 | K5: 5 | L5: 3
E6: 34C | F6: 黑色 | H6: 19.9 | I6: 16.9 | J6: 10.5 | K6: 5 | L6: 6
A7: BR-004 | B7: 内衣 | C7: Wacoal | D7: 聚拢调整型文胸 | E7: 34B | F7: 黑色 | G7: A架-2层 | H7: 25.9 | I7: 22 | J7: 14 | K7: 3 | L7: 4
E8: 36C | F8: 肤色 | H8: 25.9 | I8: 22 | J8: 14 | K8: 3 | L8: 2
A9: UN-001 | B9: 内裤 | C9: Byford | D9: 纯棉平角内裤(男) | E9: M | F9: 灰色 | G9: B架-1层 | H9: 8.9 | I9: 7.5 | J9: 4.5 | K9: 10 | L9: 15 | M9: 畅销款🔥
E10: L | F10: 灰色 | H10: 8.9 | I10: 7.5 | J10: 4.5 | K10: 10 | L10: 12 | M10: 畅销款🔥
E11: XL | F11: 黑色 | H11: 8.9 | I11: 7.5 | J11: 4.5 | K11: 10 | L11: 8
A12: UN-004 | B12: 内裤 | C12: Renoma | D12: 冰丝三角内裤(男) | E12: M | F12: 蓝色 | G12: B架-2层 | H12: 6.5 | I12: 5.5 | J12: 3.2 | K12: 10 | L12: 6
E13: L | F13: 黑色 | H13: 6.5 | I13: 5.5 | J13: 3.2 | K13: 10 | L13: 10
A14: UN-006 | B14: 内裤 | C14: Triumph | D14: 蕾丝三角内裤(女) | E14: M | F14: 粉色 | G14: B架-3层 | H14: 7.9 | I14: 6.5 | J14: 3.8 | K14: 10 | L14: 5
E15: L | F15: 肤色 | H15: 7.9 | I15: 6.5 | J15: 3.8 | K15: 10 | L15: 7
A16: SK-001 | B16: 袜子 | C16: Goldlion | D16: 商务棉袜 3双装 | E16: 均码 | F16: 黑色 | G16: C架-1层 | H16: 5.5 | I16: 4.6 | J16: 2.5 | K16: 15 | L16: 20 | M16: 3双装
E17: 均码 | F17: 深灰 | H17: 5.5 | I17: 4.6 | J17: 2.5 | K17: 15 | L17: 12 | M17: 3双装
A18: SK-003 | B18: 袜子 | C18: Puma | D18: 运动短袜(男) | E18: 均码 | F18: 白色 | G18: C架-2层 | H18: 6.9 | I18: 5.8 | J18: 3 | K18: 15 | L18: 8
A19: SK-004 | B19: 袜子 | C19: Puma | D19: 运动短袜(女) | E19: 均码 | F19: 白色 | G19: C架-2层 | H19: 6.9 | I19: 5.8 | J19: 3 | K19: 15 | L19: 10
A20: SK-005 | B20: 袜子 | C20: Happy Socks | D20: 彩色棉袜(女) | E20: 均码 | F20: 花色 | G20: C架-3层 | H20: 7.9 | I20: 6.5 | J20: 3.5 | K20: 10 | L20: 4
A21: ST-001 | B21: 裤袜 | C21: Gunze | D21: 发热保暖连裤袜 | E21: M-L | F21: 黑色 | G21: D架-1层 | H21: 15.9 | I21: 13.5 | J21: 8 | K21: 5 | L21: 3 | M21: 日本制
E22: L-LL | F22: 深灰 | H22: 15.9 | I22: 13.5 | J22: 8 | K22: 5 | L22: 5 | M22: 日本制
A23: ST-003 | B23: 裤袜 | C23: Atsugi | D23: 压力美腿连裤袜 | E23: M-L | F23: 肤色 | G23: D架-2层 | H23: 18.9 | I23: 16 | J23: 10 | K23: 3 | L23: 2

Sheet 库存总览
A1: 库存总览 — Inventory Overview
A2: 全自动汇总。进货量取自进货单，已售量取自销售开单。低于安全库存自动标红并建议补货。
A3: 商品编号 | B3: 品类 | C3: 品牌 | D3: 款式名称 | E3: 尺码 | F3: 颜色 | G3: 存放位置 | H3: 总进货量 | I3: 已售数量 | J3: 当前库存 | K3: 安全库存 | L3: 建议补货量 | M3: 库存状态
A4: BR-001 | B4: 内衣 | C4: Triumph | D4: 无钢圈舒适文胸 | E4: 34B | F4: 黑色 | G4: A架-1层 | H4: =SUMIF(进货单!D:D,A4,进货单!I:I) | I4: =SUMIF(销售开单!E:E,A4,销售开单!I:I) | J4: =H4-I4 | K4: 5 | L4: =IF(J4<K4,K4*2-J4,0) | M4: =IF(J4<=0,"缺货",IF(J4<K4,"不足","充足"))
E5: 36B | F5: 肤色 | H5: =SUMIF(进货单!D:D,A5,进货单!I:I) | I5: =SUMIF(销售开单!E:E,A5,销售开单!I:I) | J5: =H5-I5 | K5: 5 | L5: =IF(J5<K5,K5*2-J5,0) | M5: =IF(J5<=0,"缺货",IF(J5<K5,"不足","充足"))
E6: 34C | F6: 黑色 | H6: =SUMIF(进货单!D:D,A6,进货单!I:I) | I6: =SUMIF(销售开单!E:E,A6,销售开单!I:I) | J6: =H6-I6 | K6: 5 | L6: =IF(J6<K6,K6*2-J6,0) | M6: =IF(J6<=0,"缺货",IF(J6<K6,"不足","充足"))
A7: BR-004 | B7: 内衣 | C7: Wacoal | D7: 聚拢调整型文胸 | E7: 34B | F7: 黑色 | G7: A架-2层 | H7: =SUMIF(进货单!D:D,A7,进货单!I:I) | I7: =SUMIF(销售开单!E:E,A7,销售开单!I:I) | J7: =H7-I7 | K7: 3 | L7: =IF(J7<K7,K7*2-J7,0) | M7: =IF(J7<=0,"缺货",IF(J7<K7,"不足","充足"))
E8: 36C | F8: 肤色 | H8: =SUMIF(进货单!D:D,A8,进货单!I:I) | I8: =SUMIF(销售开单!E:E,A8,销售开单!I:I) | J8: =H8-I8 | K8: 3 | L8: =IF(J8<K8,K8*2-J8,0) | M8: =IF(J8<=0,"缺货",IF(J8<K8,"不足","充足"))
A9: UN-001 | B9: 内裤 | C9: Byford | D9: 纯棉平角内裤(男) | E9: M | F9: 灰色 | G9: B架-1层 | H9: =SUMIF(进货单!D:D,A9,进货单!I:I) | I9: =SUMIF(销售开单!E:E,A9,销售开单!I:I) | J9: =H9-I9 | K9: 10 | L9: =IF(J9<K9,K9*2-J9,0) | M9: =IF(J9<=0,"缺货",IF(J9<K9,"不足","充足"))
E10: L | F10: 灰色 | H10: =SUMIF(进货单!D:D,A10,进货单!I:I) | I10: =SUMIF(销售开单!E:E,A10,销售开单!I:I) | J10: =H10-I10 | K10: 10 | L10: =IF(J10<K10,K10*2-J10,0) | M10: =IF(J10<=0,"缺货",IF(J10<K10,"不足","充足"))
E11: XL | F11: 黑色 | H11: =SUMIF(进货单!D:D,A11,进货单!I:I) | I11: =SUMIF(销售开单!E:E,A11,销售开单!I:I) | J11: =H11-I11 | K11: 10 | L11: =IF(J11<K11,K11*2-J11,0) | M11: =IF(J11<=0,"缺货",IF(J11<K11,"不足","充足"))
A12: UN-004 | B12: 内裤 | C12: Renoma | D12: 冰丝三角内裤(男) | E12: M | F12: 蓝色 | G12: B架-2层 | H12: =SUMIF(进货单!D:D,A12,进货单!I:I) | I12: =SUMIF(销售开单!E:E,A12,销售开单!I:I) | J12: =H12-I12 | K12: 10 | L12: =IF(J12<K12,K12*2-J12,0) | M12: =IF(J12<=0,"缺货",IF(J12<K12,"不足","充足"))
E13: L | F13: 黑色 | H13: =SUMIF(进货单!D:D,A13,进货单!I:I) | I13: =SUMIF(销售开单!E:E,A13,销售开单!I:I) | J13: =H13-I13 | K13: 10 | L13: =IF(J13<K13,K13*2-J13,0) | M13: =IF(J13<=0,"缺货",IF(J13<K13,"不足","充足"))
A14: UN-006 | B14: 内裤 | C14: Triumph | D14: 蕾丝三角内裤(女) | E14: M | F14: 粉色 | G14: B架-3层 | H14: =SUMIF(进货单!D:D,A14,进货单!I:I) | I14: =SUMIF(销售开单!E:E,A14,销售开单!I:I) | J14: =H14-I14 | K14: 10 | L14: =IF(J14<K14,K14*2-J14,0) | M14: =IF(J14<=0,"缺货",IF(J14<K14,"不足","充足"))
E15: L | F15: 肤色 | H15: =SUMIF(进货单!D:D,A15,进货单!I:I) | I15: =SUMIF(销售开单!E:E,A15,销售开单!I:I) | J15: =H15-I15 | K15: 10 | L15: =IF(J15<K15,K15*2-J15,0) | M15: =IF(J15<=0,"缺货",IF(J15<K15,"不足","充足"))
A16: SK-001 | B16: 袜子 | C16: Goldlion | D16: 商务棉袜 3双装 | E16: 均码 | F16: 黑色 | G16: C架-1层 | H16: =SUMIF(进货单!D:D,A16,进货单!I:I) | I16: =SUMIF(销售开单!E:E,A16,销售开单!I:I) | J16: =H16-I16 | K16: 15 | L16: =IF(J16<K16,K16*2-J16,0) | M16: =IF(J16<=0,"缺货",IF(J16<K16,"不足","充足"))
E17: 均码 | F17: 深灰 | H17: =SUMIF(进货单!D:D,A17,进货单!I:I) | I17: =SUMIF(销售开单!E:E,A17,销售开单!I:I) | J17: =H17-I17 | K17: 15 | L17: =IF(J17<K17,K17*2-J17,0) | M17: =IF(J17<=0,"缺货",IF(J17<K17,"不足","充足"))
A18: SK-003 | B18: 袜子 | C18: Puma | D18: 运动短袜(男) | E18: 均码 | F18: 白色 | G18: C架-2层 | H18: =SUMIF(进货单!D:D,A18,进货单!I:I) | I18: =SUMIF(销售开单!E:E,A18,销售开单!I:I) | J18: =H18-I18 | K18: 15 | L18: =IF(J18<K18,K18*2-J18,0) | M18: =IF(J18<=0,"缺货",IF(J18<K18,"不足","充足"))
A19: SK-004 | B19: 袜子 | C19: Puma | D19: 运动短袜(女) | E19: 均码 | F19: 白色 | G19: C架-2层 | H19: =SUMIF(进货单!D:D,A19,进货单!I:I) | I19: =SUMIF(销售开单!E:E,A19,销售开单!I:I) | J19: =H19-I19 | K19: 15 | L19: =IF(J19<K19,K19*2-J19,0) | M19: =IF(J19<=0,"缺货",IF(J19<K19,"不足","充足"))
A20: SK-005 | B20: 袜子 | C20: Happy Socks | D20: 彩色棉袜(女) | E20: 均码 | F20: 花色 | G20: C架-3层 | H20: =SUMIF(进货单!D:D,A20,进货单!I:I) | I20: =SUMIF(销售开单!E:E,A20,销售开单!I:I) | J20: =H20-I20 | K20: 10 | L20: =IF(J20<K20,K20*2-J20,0) | M20: =IF(J20<=0,"缺货",IF(J20<K20,"不足","充足"))
A21: ST-001 | B21: 裤袜 | C21: Gunze | D21: 发热保暖连裤袜 | E21: M-L | F21: 黑色 | G21: D架-1层 | H21: =SUMIF(进货单!D:D,A21,进货单!I:I) | I21: =SUMIF(销售开单!E:E,A21,销售开单!I:I) | J21: =H21-I21 | K21: 5 | L21: =IF(J21<K21,K21*2-J21,0) | M21: =IF(J21<=0,"缺货",IF(J21<K21,"不足","充足"))
E22: L-LL | F22: 深灰 | H22: =SUMIF(进货单!D:D,A22,进货单!I:I) | I22: =SUMIF(销售开单!E:E,A22,销售开单!I:I) | J22: =H22-I22 | K22: 5 | L22: =IF(J22<K22,K22*2-J22,0) | M22: =IF(J22<=0,"缺货",IF(J22<K22,"不足","充足"))
A23: ST-003 | B23: 裤袜 | C23: Atsugi | D23: 压力美腿连裤袜 | E23: M-L | F23: 肤色 | G23: D架-2层 | H23: =SUMIF(进货单!D:D,A23,进货单!I:I) | I23: =SUMIF(销售开单!E:E,A23,销售开单!I:I) | J23: =H23-I23 | K23: 3 | L23: =IF(J23<K23,K23*2-J23,0) | M23: =IF(J23<=0,"缺货",IF(J23<K23,"不足","充足"))

Sheet 进货单
A1: 进货单 — Purchase / Stock-In
A2: 记录每次进货。填写日期、供应商、商品编号、数量、进货单价即可。
A3: 日期 | B3: 进货单号 | C3: 供应商 | D3: 商品编号 | E3: 品类 | F3: 款式名称 | G3: 尺码 | H3: 颜色 | I3: 进货数量 | J3: 进货单价(SGD) | K3: 进货总额(SGD) | L3: 备注
A4: 2026-06-01 | B4: PI-1001 | C4: Triumph SG | D4: BR-001 | E4: 内衣 | F4: 无钢圈舒适文胸 | G4: 34B | H4: 黑色 | I4: 10 | J4: 10.5 | K4: =I4*J4
A5: 2026-06-01 | B5: PI-1002 | C5: Triumph SG | D5: BR-002 | E5: 内衣 | F5: 无钢圈舒适文胸 | G5: 36B | H5: 肤色 | I5: 8 | J5: 10.5 | K5: =I5*J5
A6: 2026-06-01 | B6: PI-1003 | C6: Triumph SG | D6: BR-003 | E6: 内衣 | F6: 无钢圈舒适文胸 | G6: 34C | H6: 黑色 | I6: 8 | J6: 10.5 | K6: =I6*J6
A7: 2026-06-01 | B7: PI-1004 | C7: Wacoal 代理 | D7: BR-004 | E7: 内衣 | F7: 聚拢调整型文胸 | G7: 34B | H7: 黑色 | I7: 5 | J7: 14 | K7: =I7*J7
A8: 2026-06-01 | B8: PI-1005 | C8: Wacoal 代理 | D8: BR-005 | E8: 内衣 | F8: 聚拢调整型文胸 | G8: 36C | H8: 肤色 | I8: 5 | J8: 14 | K8: =I8*J8
A9: 2026-06-01 | B9: PI-1006 | C9: Byford 批发 | D9: UN-001 | E9: 内裤 | F9: 纯棉平角内裤(男) | G9: M | H9: 灰色 | I9: 20 | J9: 4.5 | K9: =I9*J9
A10: 2026-06-01 | B10: PI-1007 | C10: Byford 批发 | D10: UN-002 | E10: 内裤 | F10: 纯棉平角内裤(男) | G10: L | H10: 灰色 | I10: 20 | J10: 4.5 | K10: =I10*J10
A11: 2026-06-01 | B11: PI-1008 | C11: Byford 批发 | D11: UN-003 | E11: 内裤 | F11: 纯棉平角内裤(男) | G11: XL | H11: 黑色 | I11: 15 | J11: 4.5 | K11: =I11*J11
A12: 2026-06-01 | B12: PI-1009 | C12: Renoma 总代 | D12: UN-004 | E12: 内裤 | F12: 冰丝三角内裤(男) | G12: M | H12: 蓝色 | I12: 12 | J12: 3.2 | K12: =I12*J12
A13: 2026-06-01 | B13: PI-1010 | C13: Renoma 总代 | D13: UN-005 | E13: 内裤 | F13: 冰丝三角内裤(男) | G13: L | H13: 黑色 | I13: 12 | J13: 3.2 | K13: =I13*J13
A14: 2026-06-01 | B14: PI-1011 | C14: Triumph SG | D14: UN-006 | E14: 内裤 | F14: 蕾丝三角内裤(女) | G14: M | H14: 粉色 | I14: 10 | J14: 3.8 | K14: =I14*J14
A15: 2026-06-01 | B15: PI-1012 | C15: Triumph SG | D15: UN-007 | E15: 内裤 | F15: 蕾丝三角内裤(女) | G15: L | H15: 肤色 | I15: 10 | J15: 3.8 | K15: =I15*J15
... A25: 2026-06-08 | B25: PI-1022 | C25: Goldlion 批发 | D25: SK-001 | E25: 袜子 | F25: 商务棉袜 3双装 | G25: 均码 | H25: 黑色 | I25: 5 | J25: 2.5 | K25: =I25*J25
K26: =I26*J26

Sheet 销售开单
A1: 销售开单 — Sales Order
A2: 零售/批发分开记录。填日期、类型、商品编号、数量，单价自动匹配（零售价/批发价）。
A3: 日期 | B3: 单号 | C3: 类型 | D3: 客户 | E3: 商品编号 | F3: 品类 | G3: 款式名称 | H3: 尺码 | I3: 数量 | J3: 单价(SGD) | K3: 金额(SGD) | L3: 备注
A4: 2026-06-07 | B4: SO-1001 | C4: 零售 | D4: 散客 | E4: UN-001 | F4: 内裤 | G4: 纯棉平角内裤(男) | H4: M | I4: 3 | J4: 8.9 | K4: =I4*J4
A5: 2026-06-07 | B5: SO-1002 | C5: 零售 | D5: 散客 | E5: UN-002 | F5: 内裤 | G5: 纯棉平角内裤(男) | H5: L | I5: 2 | J5: 8.9 | K5: =I5*J5
A6: 2026-06-07 | B6: SO-1003 | C6: 零售 | D6: 散客 | E6: SK-001 | F6: 袜子 | G6: 商务棉袜 3双装 | H6: 均码 | I6: 4 | J6: 5.5 | K6: =I6*J6
A7: 2026-06-07 | B7: SO-1004 | C7: 零售 | D7: 散客 | E7: BR-001 | F7: 内衣 | G7: 无钢圈舒适文胸 | H7: 34B | I7: 1 | J7: 19.9 | K7: =I7*J7
A8: 2026-06-07 | B8: SO-1005 | C8: 零售 | D8: 散客 | E8: ST-001 | F8: 裤袜 | G8: 发热保暖连裤袜 | H8: M-L | I8: 1 | J8: 15.9 | K8: =I8*J8
A9: 2026-06-08 | B9: SO-1006 | C9: 零售 | D9: 散客 | E9: UN-001 | F9: 内裤 | G9: 纯棉平角内裤(男) | H9: M | I9: 2 | J9: 8.9 | K9: =I9*J9
A10: 2026-06-08 | B10: SO-1007 | C10: 零售 | D10: 散客 | E10: UN-006 | F10: 内裤 | G10: 蕾丝三角内裤(女) | H10: M | I10: 3 | J10: 7.9 | K10: =I10*J10
A11: 2026-06-08 | B11: SO-1008 | C11: 零售 | D11: 散客 | E11: SK-003 | F11: 袜子 | G11: 运动短袜(男) | H11: 均码 | I11: 2 | J11: 6.9 | K11: =I11*J11
A12: 2026-06-08 | B12: SO-1009 | C12: 零售 | D12: 散客 | E12: BR-002 | F12: 内衣 | G12: 无钢圈舒适文胸 | H12: 36B | I12: 1 | J12: 19.9 | K12: =I12*J12
A13: 2026-06-09 | B13: SO-1010 | C13: 零售 | D13: 散客 | E13: UN-002 | F13: 内裤 | G13: 纯棉平角内裤(男) | H13: L | I13: 4 | J13: 8.9 | K13: =I13*J13
A14: 2026-06-09 | B14: SO-1011 | C14: 零售 | D14: 散客 | E14: UN-004 | F14: 内裤 | G14: 冰丝三角内裤(男) | H14: M | I14: 2 | J14: 6.5 | K14: =I14*J14
A15: 2026-06-09 | B15: SO-1012 | C15: 零售 | D15: 散客 | E15: SK-002 | F15: 袜子 | G15: 商务棉袜 3双装 | H15: 均码 | I15: 3 | J15: 5.5 | K15: =I15*J15
... A38: 2026-06-12 | B38: SO-1035 | C38: 批发 | D38: 美美服饰 | E38: BR-002 | F38: 内衣 | G38: 无钢圈舒适文胸 | H38: 36B | I38: 5 | J38: 16.9 | K38: =I38*J38
K39: =I39*J39

Sheet 记账汇总
A1: 记账汇总 — Daily Accounting
A2: 全自动汇总。每日销售额、成本、利润一键查看。数据取自进货单和销售开单。
A3: 日期 | B3: 进货总额(SGD) | C3: 零售额(SGD) | D3: 零售件数 | E3: 批发额(SGD) | F3: 批发件数 | G3: 总销售额(SGD) | H3: 总成本(SGD) | I3: 总利润(SGD) | J3: 利润率
A4: 2026-06-01 | B4: =SUMIF(进货单!A:A,A4,进货单!K:K) | C4: =SUMIFS(销售开单!K:K,销售开单!A:A,A4,销售开单!C:C,"零售") | D4: =SUMIFS(销售开单!I:I,销售开单!A:A,A4,销售开单!C:C,"零售") | E4: =SUMIFS(销售开单!K:K,销售开单!A:A,A4,销售开单!C:C,"批发") | F4: =SUMIFS(销售开单!I:I,销售开单!A:A,A4,销售开单!C:C,"批发") | G4: =C4+E4 | H4: =IF(C4+E4=0,0,(C4+E4)*SUMPRODUCT((商品目录!H4:H23)*(商品目录!J4:J23))/SUM(商品目录!H4:H23)) | I4: =G4-H4 | J4: =IF(G4=0,0,I4/G4)
A5: 2026-06-07 | B5: =SUMIF(进货单!A:A,A5,进货单!K:K) | C5: =SUMIFS(销售开单!K:K,销售开单!A:A,A5,销售开单!C:C,"零售") | D5: =SUMIFS(销售开单!I:I,销售开单!A:A,A5,销售开单!C:C,"零售") | E5: =SUMIFS(销售开单!K:K,销售开单!A:A,A5,销售开单!C:C,"批发") | F5: =SUMIFS(销售开单!I:I,销售开单!A:A,A5,销售开单!C:C,"批发") | G5: =C5+E5 | H5: =IF(C5+E5=0,0,(C5+E5)*SUMPRODUCT((商品目录!H4:H23)*(商品目录!J4:J23))/SUM(商品目录!H4:H23)) | I5: =G5-H5 | J5: =IF(G5=0,0,I5/G5)
A6: 2026-06-08 | B6: =SUMIF(进货单!A:A,A6,进货单!K:K) | C6: =SUMIFS(销售开单!K:K,销售开单!A:A,A6,销售开单!C:C,"零售") | D6: =SUMIFS(销售开单!I:I,销售开单!A:A,A6,销售开单!C:C,"零售") | E6: =SUMIFS(销售开单!K:K,销售开单!A:A,A6,销售开单!C:C,"批发") | F6: =SUMIFS(销售开单!I:I,销售开单!A:A,A6,销售开单!C:C,"批发") | G6: =C6+E6 | H6: =IF(C6+E6=0,0,(C6+E6)*SUMPRODUCT((商品目录!H4:H23)*(商品目录!J4:J23))/SUM(商品目录!H4:H23)) | I6: =G6-H6 | J6: =IF(G6=0,0,I6/G6)
A7: 2026-06-09 | B7: =SUMIF(进货单!A:A,A7,进货单!K:K) | C7: =SUMIFS(销售开单!K:K,销售开单!A:A,A7,销售开单!C:C,"零售") | D7: =SUMIFS(销售开单!I:I,销售开单!A:A,A7,销售开单!C:C,"零售") | E7: =SUMIFS(销售开单!K:K,销售开单!A:A,A7,销售开单!C:C,"批发") | F7: =SUMIFS(销售开单!I:I,销售开单!A:A,A7,销售开单!C:C,"批发") | G7: =C7+E7 | H7: =IF(C7+E7=0,0,(C7+E7)*SUMPRODUCT((商品目录!H4:H23)*(商品目录!J4:J23))/SUM(商品目录!H4:H23)) | I7: =G7-H7 | J7: =IF(G7=0,0,I7/G7)
A8: 2026-06-10 | B8: =SUMIF(进货单!A:A,A8,进货单!K:K) | C8: =SUMIFS(销售开单!K:K,销售开单!A:A,A8,销售开单!C:C,"零售") | D8: =SUMIFS(销售开单!I:I,销售开单!A:A,A8,销售开单!C:C,"零售") | E8: =SUMIFS(销售开单!K:K,销售开单!A:A,A8,销售开单!C:C,"批发") | F8: =SUMIFS(销售开单!I:I,销售开单!A:A,A8,销售开单!C:C,"批发") | G8: =C8+E8 | H8: =IF(C8+E8=0,0,(C8+E8)*SUMPRODUCT((商品目录!H4:H23)*(商品目录!J4:J23))/SUM(商品目录!H4:H23)) | I8: =G8-H8 | J8: =IF(G8=0,0,I8/G8)
A9: 2026-06-11 | B9: =SUMIF(进货单!A:A,A9,进货单!K:K) | C9: =SUMIFS(销售开单!K:K,销售开单!A:A,A9,销售开单!C:C,"零售") | D9: =SUMIFS(销售开单!I:I,销售开单!A:A,A9,销售开单!C:C,"零售") | E9: =SUMIFS(销售开单!K:K,销售开单!A:A,A9,销售开单!C:C,"批发") | F9: =SUMIFS(销售开单!I:I,销售开单!A:A,A9,销售开单!C:C,"批发") | G9: =C9+E9 | H9: =IF(C9+E9=0,0,(C9+E9)*SUMPRODUCT((商品目录!H4:H23)*(商品目录!J4:J23))/SUM(商品目录!H4:H23)) | I9: =G9-H9 | J9: =IF(G9=0,0,I9/G9)
A10: 2026-06-12 | B10: =SUMIF(进货单!A:A,A10,进货单!K:K) | C10: =SUMIFS(销售开单!K:K,销售开单!A:A,A10,销售开单!C:C,"零售") | D10: =SUMIFS(销售开单!I:I,销售开单!A:A,A10,销售开单!C:C,"零售") | E10: =SUMIFS(销售开单!K:K,销售开单!A:A,A10,销售开单!C:C,"批发") | F10: =SUMIFS(销售开单!I:I,销售开单!A:A,A10,销售开单!C:C,"批发") | G10: =C10+E10 | H10: =IF(C10+E10=0,0,(C10+E10)*SUMPRODUCT((商品目录!H4:H23)*(商品目录!J4:J23))/SUM(商品目录!H4:H23)) | I10: =G10-H10 | J10: =IF(G10=0,0,I10/G10)
A11: 2026-06-13 | B11: =SUMIF(进货单!A:A,A11,进货单!K:K) | C11: =SUMIFS(销售开单!K:K,销售开单!A:A,A11,销售开单!C:C,"零售") | D11: =SUMIFS(销售开单!I:I,销售开单!A:A,A11,销售开单!C:C,"零售") | E11: =SUMIFS(销售开单!K:K,销售开单!A:A,A11,销售开单!C:C,"批发") | F11: =SUMIFS(销售开单!I:I,销售开单!A:A,A11,销售开单!C:C,"批发") | G11: =C11+E11 | H11: =IF(C11+E11=0,0,(C11+E11)*SUMPRODUCT((商品目录!H4:H23)*(商品目录!J4:J23))/SUM(商品目录!H4:H23)) | I11: =G11-H11 | J11: =IF(G11=0,0,I11/G11)
A12: 合计 | B12: =SUM(B4:B11) | C12: =SUM(C4:C11) | D12: =SUM(D4:D11) | E12: =SUM(E4:E11) | F12: =SUM(F4:F11) | G12: =SUM(G4:G11) | H12: =SUM(H4:H11) | I12: =SUM(I4:I11) | J12: =SUM(J4:J11)
